lastfm_backup_cli/main.py
lastfm_backup_cli-0.2.2.dist-info/entry_points.txt
lastfm_backup_cli-0.2.2.dist-info/LICENSE
lastfm_backup_cli-0.2.2.dist-info/WHEEL
lastfm_backup_cli-0.2.2.dist-info/METADATA
lastfm_backup_cli-0.2.2.dist-info/RECORD
