Metadata-Version: 2.1
Name: lastfm-backup-cli
Version: 0.2.2
Summary: Super-simple CLI tool for backing up Last.fm scrobbling data
Home-page: https://github.com/emkor/lastfm-backup-cli
License: MIT
Keywords: lastfm,last.fm,scrobble,backup
Author: emkor93
Author-email: emkor93@gmail.com
Requires-Python: >=3.7,<4.0
Classifier: License :: OSI Approved :: MIT License
Classifier: Programming Language :: Python :: 3
Classifier: Programming Language :: Python :: 3.7
Classifier: Programming Language :: Python :: 3.8
Classifier: Programming Language :: Python :: 3.9
Requires-Dist: pylast (>=4.2.1,<5.0.0)
Project-URL: Repository, https://github.com/emkor/lastfm-backup-cli
